rhinoMorph.py
rhinoMorph/lib/rhino.jar
rhinoMorph/resource/afterNumber_MethodDeleted.txt
rhinoMorph/resource/alsoXR.txt
rhinoMorph/resource/complexStem_MethodDeleted.txt
rhinoMorph/resource/ending_MethodDeleted.txt
rhinoMorph/resource/koreanName.txt
rhinoMorph/resource/stem_MethodDeleted.txt
rhinoMorph-4.0.4.dist-info/METADATA
rhinoMorph-4.0.4.dist-info/WHEEL
rhinoMorph-4.0.4.dist-info/top_level.txt
rhinoMorph-4.0.4.dist-info/RECORD
