Metadata-Version: 2.1
Name: rhinoMorph
Version: 4.0.4
Summary: Morphological Analyzer for Korean
Home-page: https://blog.naver.com/lingua/221537630069
Author: Sukjae Choi
Author-email: lingua72@gmail.com
License: MIT
Platform: UNKNOWN
Requires-Python: >=3
